{
  "Бытие": 1,
  "Исход": 2,
  "Левит": 3,
  "Числа": 4,
  "Второзаконие": 5,
  "Иисус Навин": 6,
  "Судей": 7,
  "Руфь": 8,
  "1 Царств": 9,
  "2 Царств": 10,
  "3 Царств": 11,
  "4 Царств": 12,
  "1 Паралипоменон": 13,
  "2 Паралипоменон": 14,
  "Ездра": 15,
  "Неемия": 16,
  "Есфирь": 17,
  "Иов": 18,
  "Псалтирь": 19,
  "Притчи": 20,
  "Екклесиаст": 21,
  "Песнь Песней": 22,
  "Исаия": 23,
  "Иеремия": 24,
  "Плач Иеремии": 25,
  "Иезекииль": 26,
  "Даниил": 27,
  "Осия": 28,
  "Иоиль": 29,
  "Амос": 30,
  "Авдий": 31,
  "Иона": 32,
  "Михей": 33,
  "Наум": 34,
  "Аввакум": 35,
  "Софония": 36,
  "Аггей": 37,
  "Захария": 38,
  "Малахия": 39,
  "Матфей": 40,
  "Марк": 41,
  "Лука": 42,
  "Иоанн": 43,
  "Деяния": 44,
  "Римлянам": 45,
  "1 Коринфянам": 46,
  "2 Коринфянам": 47,
  "Галатам": 48,
  "Ефесянам": 49,
  "Филиппийцам": 50,
  "Колосянам": 51,
  "1 Фессалоникийцам": 52,
  "2 Фессалоникийцам": 53,
  "1 Тимофею": 54,
  "2 Тимофею": 55,
  "Титу": 56,
  "Филимону": 57,
  "Евреям": 58,
  "Иаков": 59,
  "1 Петра": 60,
  "2 Петра": 61,
  "1 Иоанна": 62,
  "2 Иоанна": 63,
  "3 Иоанна": 64,
  "Иуда": 65,
  "Откровение": 66
}